{
  "GlobalWhite": "#ffffff",
  "GlobalDark": "#000000",
  "GlobalPurple50": "#f5e6fc",
  "GlobalPurple100": "#e6bff9",
  "GlobalPurple200": "#d694f6",
  "GlobalPurple300": "#c566f3",
  "GlobalPurple400": "#b73ef0",
  "GlobalPurple500": "#a800eb",
  "GlobalPurple600": "#9607e5",
  "GlobalPurple700": "#7c0ade",
  "GlobalPurple800": "#630bd9",
  "GlobalPurple900": "#150dd2",
  "GlobalSemanticDanger": "#fe8900",
  "GlobalXSmall": "8",
  "GlobalSmall": "12",
  "GlobalMiddle": "16",
  "GlobalLarge": "24",
  "GlobalRadiusSmall": "6"
}